corpusloom/__init__.py
corpusloom/chunking.py
corpusloom/cli.py
corpusloom/client.py
corpusloom/exceptions.py
corpusloom/json_mode.py
corpusloom/models.py
corpusloom/py.typed
corpusloom/retrieval.py
corpusloom/store.py
corpusloom/utils.py
corpus_loom-0.3.1.dist-info/METADATA
corpus_loom-0.3.1.dist-info/WHEEL
corpus_loom-0.3.1.dist-info/entry_points.txt
corpus_loom-0.3.1.dist-info/top_level.txt
corpus_loom-0.3.1.dist-info/RECORD
