Metadata-Version: 2.4
Name: corpus-loom
Version: 0.3.1
Summary: CorpusLoom: chunking, retrieval, JSON-mode, and a CLI (cloom) for Ollama
Author-email: Ethan Leas <ethan.leas@gmail.com>
License: MIT License
Requires-Python: >=3.9
Requires-Dist: requests>=2.31.0
Provides-Extra: json
Requires-Dist: pydantic>=1.10; extra == "json"
Provides-Extra: dev
Requires-Dist: pytest>=7.4; extra == "dev"
Requires-Dist: ruff>=0.5.0; extra == "dev"
Requires-Dist: mypy>=1.8; extra == "dev"
Requires-Dist: pytest-cov>=4.1; extra == "dev"
Requires-Dist: mypy>=1.8; extra == "dev"
Requires-Dist: ruff>=0.5.0; extra == "dev"
